scratchapi2/__init__.py
scratchapi2/api.py
scratchapi2/excs.py
scratchapi2/front.py
scratchapi2/gclass.py
scratchapi2/misc.py
scratchapi2/translate.py
scratchapi2/user.py
scratchapi2-1.5.dist-info/LICENSE
scratchapi2-1.5.dist-info/METADATA
scratchapi2-1.5.dist-info/WHEEL
scratchapi2-1.5.dist-info/top_level.txt
scratchapi2-1.5.dist-info/RECORD
