Metadata-Version: 2.1
Name: scratchapi2
Version: 1.5
Summary: The New Scratch API Client.
Home-page: https://github.com/apple502j/scratchapi2
Author: Apple502j
License: GPLv3+
Keywords: scratch api requests
Platform: UNKNOWN
Classifier: Development Status :: 5 - Production/Stable
Classifier: License :: OSI Approved :: GNU General Public License v3 or later (GPLv3+)
Classifier: Natural Language :: English
Classifier: Natural Language :: Japanese
Classifier: Programming Language :: Python :: 3.6
Classifier: Programming Language :: Python :: 3 :: Only
Classifier: Programming Language :: Python :: Implementation :: CPython
Classifier: Topic :: Education
Classifier: Topic :: Software Development :: Libraries :: Python Modules
Requires-Python: >=3.0
Requires-Dist: requests
